latex_generator/__init__.py
latex_generator/latex_generator.py
texcellent_wondertex_texas_latex_generator-0.1.0.dist-info/licenses/LICENSE
texcellent_wondertex_texas_latex_generator-0.1.0.dist-info/METADATA
texcellent_wondertex_texas_latex_generator-0.1.0.dist-info/WHEEL
texcellent_wondertex_texas_latex_generator-0.1.0.dist-info/top_level.txt
texcellent_wondertex_texas_latex_generator-0.1.0.dist-info/RECORD
