Metadata-Version: 2.4
Name: texcellent_wondertex_texas_latex_generator
Version: 0.1.0
Summary: A library to generate LaTeX code for tables and images.
Home-page: https://github.com/jeck5iv/pythonHW
Author: Kalinin Ivan
Author-email: jeck5ivk@gmail.com
License: MIT
Classifier: Programming Language :: Python :: 3
Classifier: License :: OSI Approved :: MIT License
Classifier: Operating System :: OS Independent
Requires-Python: >=3.8
License-File: LICENSE
Dynamic: author
Dynamic: author-email
Dynamic: classifier
Dynamic: description
Dynamic: description-content-type
Dynamic: home-page
Dynamic: license
Dynamic: license-file
Dynamic: requires-python
Dynamic: summary
